Metadata-Version: 2.1
Name: avinash-ai
Version: 2.0.4
Summary: Build your own ML
